chroma_craft/__init__.py
chroma_craft/__main__.py
chroma_craft/tools.py
chroma_craft-0.1.0.dist-info/LICENSE
chroma_craft-0.1.0.dist-info/METADATA
chroma_craft-0.1.0.dist-info/WHEEL
chroma_craft-0.1.0.dist-info/top_level.txt
chroma_craft-0.1.0.dist-info/RECORD
