Metadata-Version: 2.1
Name: chroma-craft
Version: 0.1.0
Summary: A simple library that automates the generation of distinguishable colors paletes, and offers other color tools.
Author-email: Felix-Pedro <croma_craft@auneria.com>
License: MIT License
Project-URL: Homepage, https://github.com/Felix-Pedro/ChromaCraft
Keywords: color,colors,distinguish,distinguishable,different,unique,palette,distinct,differenciable,color palette,color palettes,color palette generator,distinct colors,distinct color,distinguishable colors,unique color palette,unique color palettes,unique colors
Classifier: License :: OSI Approved :: MIT License
Classifier: Programming Language :: Python
Classifier: Programming Language :: Python :: 3
License-File: LICENSE
Requires-Dist: matplotlib
Requires-Dist: numpy
Requires-Dist: tqdm
Requires-Dist: seaborn
Provides-Extra: dev
Requires-Dist: black ; extra == 'dev'
Requires-Dist: pip-tools ; extra == 'dev'
Requires-Dist: pytest ; extra == 'dev'
Requires-Dist: build ; extra == 'dev'
Requires-Dist: twine ; extra == 'dev'
